LICENSE
README.md
setup.py
gpx_analysis/__init__.py
gpx_analysis/__main__.py
gpx_analysis/app.py
gpx_analysis/components.py
gpx_analysis/gpx_parser.py
gpx_analysis/graph_handler.py
gpx_analysis/gui.py
gpx_analysis/gui_control_menu.py
gpx_analysis/gui_finishline_menu.py
gpx_analysis/gui_playback_menu.py
gpx_analysis/gui_stats_menu.py
gpx_analysis/sporting.py
gpx_analysis/stats_graph_handler.py
gpx_analysis_edf1101.egg-info/PKG-INFO
gpx_analysis_edf1101.egg-info/SOURCES.txt
gpx_analysis_edf1101.egg-info/dependency_links.txt
gpx_analysis_edf1101.egg-info/requires.txt
gpx_analysis_edf1101.egg-info/top_level.txt