Metadata-Version: 2.1
Name: gpx-analysis-edf1101
Version: 1.7
Summary: GPX Analysis Program
Home-page: https://github.com/edf1101/Rowing-GPX-Analysis
Author: edf1101
Author-email: blank@blank.com
Classifier: Programming Language :: Python :: 3
Classifier: License :: OSI Approved :: MIT License
Classifier: Operating System :: OS Independent
Requires-Python: >=3.11
License-File: LICENSE
